django_ilmoitin/__init__.py
django_ilmoitin/admin.py
django_ilmoitin/apps.py
django_ilmoitin/dummy_context.py
django_ilmoitin/models.py
django_ilmoitin/registry.py
django_ilmoitin/utils.py
django_ilmoitin/api/__init__.py
django_ilmoitin/api/schema/__init__.py
django_ilmoitin/api/schema/queries.py
django_ilmoitin/api/schema/types.py
django_ilmoitin/migrations/0001_initial.py
django_ilmoitin/migrations/0002_add_admin_notifications.py
django_ilmoitin/migrations/0003_remove_notificationtemplate_from_email.py
django_ilmoitin/migrations/0004_update_translation_master_type.py
django_ilmoitin/migrations/0005_bigauto_pk_field.py
django_ilmoitin/migrations/0006_alter_notificationtemplatetranslation_id.py
django_ilmoitin/migrations/0007_alter_notificationtemplate_admins_to_notify.py
django_ilmoitin/migrations/__init__.py
django_ilmoitin/static/admin/css/modal.css
django_ilmoitin/static/admin/js/preview.js
django_ilmoitin/templates/admin/preview_template.html
django_ilmoitin-0.7.1.dist-info/LICENSE
django_ilmoitin-0.7.1.dist-info/METADATA
django_ilmoitin-0.7.1.dist-info/WHEEL
django_ilmoitin-0.7.1.dist-info/top_level.txt
django_ilmoitin-0.7.1.dist-info/RECORD
