Metadata-Version: 2.1
Name: django_ilmoitin
Version: 0.7.1
Summary: Django app for sending notifications.
Home-page: https://github.com/City-of-Helsinki/django-ilmoitin
Author: City of Helsinki
Author-email: dev@hel.fi
License: MIT License
Classifier: Environment :: Web Environment
Classifier: Framework :: Django
Classifier: Framework :: Django :: 3.2
Classifier: Framework :: Django :: 4.0
Classifier: Framework :: Django :: 4.1
Classifier: Framework :: Django :: 4.2
Classifier: Intended Audience :: Developers
Classifier: License :: OSI Approved :: MIT License
Classifier: Operating System :: OS Independent
Classifier: Programming Language :: Python
Classifier: Programming Language :: Python :: 3.8
Classifier: Programming Language :: Python :: 3.9
Classifier: Programming Language :: Python :: 3.10
Classifier: Programming Language :: Python :: 3.11
Classifier: Programming Language :: Python :: 3.12
Classifier: Topic :: Internet :: WWW/HTTP
Classifier: Topic :: Internet :: WWW/HTTP :: Dynamic Content
License-File: LICENSE
Requires-Dist: Django >=3.2
Requires-Dist: django-parler >=2.0
Requires-Dist: django-anymail
Requires-Dist: django-mailer
Requires-Dist: jinja2
Provides-Extra: graphql_api
Requires-Dist: graphene >=2.0 ; extra == 'graphql_api'
Requires-Dist: graphene-django ; extra == 'graphql_api'
Requires-Dist: graphql-core <3,>=2.1 ; extra == 'graphql_api'
Requires-Dist: graphql-relay <3,>=2 ; extra == 'graphql_api'
